witmotion/__init__.py
witmotion/protocol.py
witmotion/cmd/__init__.py
witmotion/cmd/debug.py
witmotion-0.0.1.dev0.dist-info/LICENSE
witmotion-0.0.1.dev0.dist-info/METADATA
witmotion-0.0.1.dev0.dist-info/WHEEL
witmotion-0.0.1.dev0.dist-info/entry_points.txt
witmotion-0.0.1.dev0.dist-info/top_level.txt
witmotion-0.0.1.dev0.dist-info/RECORD
