Metadata-Version: 2.1
Name: witmotion
Version: 0.0.1.dev0
Summary: API for Witmotion IMUs, including HWT905
Home-page: https://github.com/storborg/witmotion
Author: Scott Torborg
Author-email: storborg@gmail.com
License: MIT
Keywords: witmotion hwt905 imu
Platform: UNKNOWN
Classifier: Development Status :: 3 - Alpha
Classifier: License :: OSI Approved :: MIT License
Classifier: Programming Language :: Python :: 3
License-File: LICENSE
Requires-Dist: pyserial
